enginelib/__init__.py
enginelib/claim_focus.py
enginelib/claim_insurance_focus.py
enginelib/claim_line_focus.py
enginelib/combo_matcher.py
enginelib/comparator.py
enginelib/decor/__init__.py
enginelib/decor/config.py
enginelib/decor/errors.py
enginelib/decor/flow.py
enginelib/decor/node.py
enginelib/decor/policy.py
enginelib/decor/predicate.py
enginelib/decor/registry.py
enginelib/decor/result.py
enginelib/decor/traversal.py
enginelib/decor/tree.py
enginelib/errors.py
enginelib/insights.py
enginelib/matchers/__init__.py
enginelib/matchers/same_date.py
enginelib/matchers/same_patient/__init__.py
enginelib/matchers/same_patient/policy.py
enginelib/matchers/same_patient/predicates.py
enginelib/matchers/same_patient/result.py
enginelib/matchers/same_provider/__init__.py
enginelib/matchers/same_provider/policy.py
enginelib/matchers/same_provider/predicates.py
enginelib/matchers/same_provider/result.py
enginelib/matchers/same_provider/taxonomy.py
enginelib/mpe/__init__.py
enginelib/mpe/interface.py
enginelib/mpe/multi_policy.py
enginelib/mpe/subtrees/__init__.py
enginelib/mpe/subtrees/exception.py
enginelib/mpe/subtrees/prerequisite.py
enginelib/mpe/utils/__init__.py
enginelib/mpe/utils/age_in_uom.py
enginelib/mpe/utils/age_relation.py
enginelib/rds/__init__.py
enginelib/rds/client.py
enginelib/rds/drugs_and_biologicals.py
enginelib/rds/florida_medicaid.py
enginelib/rds/icd10.py
enginelib/rds/mfs.py
enginelib/rds/mfs2.py
enginelib/rds/multipolicy.py
enginelib/rds/ncci_mue_medicaid.py
enginelib/rds/ncci_mue_medicare.py
enginelib/rds/ncci_ptp_medicaid.py
enginelib/rds/ncci_ptp_medicare.py
enginelib/rds/new_york_medicaid.py
enginelib/rds/provider_taxonomy_crosswalk.py
enginelib/rds/utils.py
enginelib/resources.py
enginelib/simple_insight.py
enginelib/tree_node.py
enginelib/types.py
enginelib/utils.py
rialtic_engine_lib_py-1.13.36.dist-info/WHEEL
rialtic_engine_lib_py-1.13.36.dist-info/METADATA
rialtic_engine_lib_py-1.13.36.dist-info/RECORD
