Metadata-Version: 2.1
Name: rialtic-engine-lib-py
Version: 1.13.36
Summary: Python Library for development of Rialtic Insight Engines
Home-page: https://rialtic.io
License: Apache-2.0
Keywords: rialtic,insight,engine,library
Author: Rialtic
Author-email: engines.data@rialtic.io
Requires-Python: >=3.7,<4.0
Classifier: License :: OSI Approved :: Apache Software License
Classifier: Operating System :: OS Independent
Classifier: Programming Language :: Python :: 3
Classifier: Programming Language :: Python :: 3.10
Classifier: Programming Language :: Python :: 3.7
Classifier: Programming Language :: Python :: 3.8
Classifier: Programming Language :: Python :: 3.9
Classifier: Topic :: Software Development :: Libraries
Requires-Dist: deprecation (>2.0)
Requires-Dist: fhir.resources (>=6.1.0,<7.0.0)
Requires-Dist: insight-engine-schema-python (>=0.3,<0.4)
Requires-Dist: rialtic-data-dev-py (>=1.1,<2.0)
Requires-Dist: sphinx (>=4.1.2,<5.0.0)
Project-URL: Repository, https://github.com/rialtic-community/rialtic-engine-lib-py
